expect_def/__about__.py
expect_def/__init__.py
expect_def-0.0.7.dist-info/METADATA
expect_def-0.0.7.dist-info/WHEEL
expect_def-0.0.7.dist-info/licenses/LICENSE.txt
expect_def-0.0.7.dist-info/RECORD
