Metadata-Version: 2.1
Name: expect-def
Version: 0.0.7
Project-URL: Documentation, https://github.com/charlesetc/expect-def#readme
Project-URL: Issues, https://github.com/charlesetc/expect-def/issues
Project-URL: Source, https://github.com/charlesetc/expect-def
Author-email: Charles Chamberlain <charles@nrwhl.xyz>
License-Expression: MIT
License-File: LICENSE.txt
Classifier: Development Status :: 4 - Beta
Classifier: Programming Language :: Python
Classifier: Programming Language :: Python :: 3.7
Classifier: Programming Language :: Python :: 3.8
Classifier: Programming Language :: Python :: 3.9
Classifier: Programming Language :: Python :: 3.10
Classifier: Programming Language :: Python :: 3.11
Classifier: Programming Language :: Python :: Implementation :: CPython
Classifier: Programming Language :: Python :: Implementation :: PyPy
Requires-Python: >=3.7
Requires-Dist: clize
